LICENSE
MANIFEST.in
README.md
setup.py
terminal_palette/__init__.py
terminal_palette.egg-info/PKG-INFO
terminal_palette.egg-info/SOURCES.txt
terminal_palette.egg-info/dependency_links.txt
terminal_palette.egg-info/top_level.txt